gwot/__init__.py
gwot/altsolver.py
gwot/bridgesampling.py
gwot/lambertw.py
gwot/models.py
gwot/reprog_dataset_utils.py
gwot/sim.py
gwot/ts.py
gwot/util.py
gwot-0.0.12.dist-info/LICENSE
gwot-0.0.12.dist-info/METADATA
gwot-0.0.12.dist-info/WHEEL
gwot-0.0.12.dist-info/top_level.txt
gwot-0.0.12.dist-info/RECORD
