Metadata-Version: 2.1
Name: gwot
Version: 0.0.12
Summary: gWOT
Home-page: https://github.com/zsteve/gwot
Author: Stephen Zhang
Author-email: syz@math.ubc.ca
License: UNKNOWN
Platform: UNKNOWN
Classifier: Programming Language :: Python :: 3
Classifier: License :: OSI Approved :: MIT License
Classifier: Operating System :: OS Independent
Requires-Python: >=3.6
